MANIFEST.in
README.rst
pyproject.toml
setup.cfg
setup.py
adapya/__init__.py
adapya/base/scripts/ftpz.py
adapya/base/scripts/getfilez.py
adapya/base/scripts/jesjob.py
adapya/base/scripts/smfreaderz.py
adapya/base/LICENSE-2.0.txt
adapya/base/NOTICE.txt
adapya/base/__init__.py
adapya/base/conv.py
adapya/base/datamap.py
adapya/base/defs.py
adapya/base/dtconv.py
adapya/base/dump.py
adapya/base/ecscodec.py
adapya/base/ftptoolz.py
adapya/base/future.py
adapya/base/jconfig.py
adapya/base/recipes.py
adapya/base/recordio.py
adapya/base/smfrecordz.py
adapya/base/stck.py
adapya/base/touch.py
adapya/base/xtea.py
adapya/base/zos.py
adapya/base/doc/conf.py
adapya/base/scripts/__init__.py
adapya/base/scripts/ftpz.py
adapya/base/scripts/getfilez.py
adapya/base/scripts/jesjob.py
adapya/base/scripts/smfreaderz.py
adapya/base/test/__init__.py
adapya/base/test/test_conv.py
adapya/base/test/test_datamap.py
adapya/base/test/test_datamap2.py
adapya/base/test/test_dummy_mini.py
adapya/base/test/test_dummy_nose.py
adapya/base/test/test_dummy_pytest.py
adapya/base/test/test_dump.py
adapya/base/test/test_stck.py
adapya/base/test/test_vmap.py
adapya_base.egg-info/PKG-INFO
adapya_base.egg-info/SOURCES.txt
adapya_base.egg-info/dependency_links.txt
adapya_base.egg-info/namespace_packages.txt
adapya_base.egg-info/not-zip-safe
adapya_base.egg-info/top_level.txt